graphis_planes/__init__.py
graphis_planes/modulo.py
graphis_planes/modulo2.py
graphis_planes-0.2.dist-info/METADATA
graphis_planes-0.2.dist-info/WHEEL
graphis_planes-0.2.dist-info/top_level.txt
graphis_planes-0.2.dist-info/RECORD
