Metadata-Version: 2.1
Name: graphis_planes
Version: 0.2
Summary: Esta es una libreria para generar graficos en 2D, añadiendo herramientas y utilidades extras para mejorar la generacion de graficos.
Home-page: https://github.com/CCFTS/graphics-plane
Author: Damian Zsiros, Alejandro Beltran, Alejandro de La Esprella, Cristian Cuadrado
Author-email: damjeronzalez23@gmail.com
Classifier: Programming Language :: Python :: 3
Classifier: License :: OSI Approved :: MIT License
Requires-Python: >=3.6
